geo_augment/__init__.py
geo_augment/config.py
geo_augment/cli/__init__.py
geo_augment/cli/main.py
geo_augment/evaluation/__init__.py
geo_augment/evaluation/distribution.py
geo_augment/evaluation/floods.py
geo_augment/evaluation/visual.py
geo_augment/io/__init__.py
geo_augment/io/preprocess.py
geo_augment/io/raster.py
geoaugment-0.1.3.dist-info/licenses/LICENSE
geoaugment-0.1.3.dist-info/METADATA
geoaugment-0.1.3.dist-info/WHEEL
geoaugment-0.1.3.dist-info/entry_points.txt
geoaugment-0.1.3.dist-info/top_level.txt
geoaugment-0.1.3.dist-info/RECORD
