Metadata-Version: 2.4
Name: geoaugment
Version: 0.1.3
Summary: Constraint-aware synthetic geospatial data augmentation engine for GeoAI
Home-page: https://github.com/93Chidiebere/GeoAugment-Algorithm
Author: Chidiebere V. Christopher
Author-email: vchidiebere.vc@gmail.com
Classifier: Programming Language :: Python :: 3
Classifier: License :: OSI Approved :: MIT License
Classifier: Operating System :: OS Independent
Requires-Python: >=3.10
License-File: LICENSE
Requires-Dist: numpy
Requires-Dist: scipy
Requires-Dist: pandas
Requires-Dist: rasterio
Requires-Dist: torch
Requires-Dist: torchgeo
Requires-Dist: click
Requires-Dist: scikit-learn
Requires-Dist: pyyaml
Dynamic: author
Dynamic: author-email
Dynamic: classifier
Dynamic: description
Dynamic: description-content-type
Dynamic: home-page
Dynamic: license-file
Dynamic: requires-dist
Dynamic: requires-python
Dynamic: summary
